{
 "code":200,
 "smallHome":["1438240218993385473","1438240330589474818"],
 "dyj":[],
 "jxnc":"{\"smp\":\"60a620f96e505406586b8e249eda3ad8\",\"active\":\"jdnc_1_3yuanyoutao210616_2\",\"joinnum\":1}@{\"smp\":\"3c8c18f1639c25fc0764a0044bf7cb4d\",\"active\":\"jdnc_1_3yuanshupian210601_2\",\"joinnum\":1}",
 "mohe":["4c0c8b93-6ddb-4d16-b20d-f0fef9cafaa0"],
 "cash":["eU9YaLi1ZK0m9jvRz3VC0w", "eU9YJI_1EYtGhj-Nii5C", "Ih4xbu61b_kh9W66iw", "IRs3ae6yZvwgnjM"],
 "redBag":["354141494"],
 "invokeKey":"RtKLB8euDo7KwsO0"
}
